quantmaster/__init__.py
quantmaster/features/__init__.py
quantmaster/features/microstructure.py
quantmaster/features/momentum.py
quantmaster/features/regime.py
quantmaster/features/returns.py
quantmaster/features/risk.py
quantmaster/features/statistical.py
quantmaster/features/trend.py
quantmaster/features/utils.py
quantmaster/features/volatility.py
quantmaster/features/volume.py
quantmaster-0.1.3.dist-info/licenses/LICENSE
quantmaster-0.1.3.dist-info/METADATA
quantmaster-0.1.3.dist-info/WHEEL
quantmaster-0.1.3.dist-info/top_level.txt
quantmaster-0.1.3.dist-info/RECORD
