Metadata-Version: 2.4
Name: quantmaster
Version: 0.1.3
Summary: Biblioteca de features quantitativas para algorithmic trading (OHLCV -> features).
License: MIT License
Project-URL: Homepage, https://github.com/wolfox33/quantmaster
Project-URL: Source, https://github.com/wolfox33/quantmaster
Project-URL: Documentation, https://wolfox33.github.io/quantmaster/
Project-URL: Issues, https://github.com/wolfox33/quantmaster/issues
Requires-Python: >=3.10
License-File: LICENSE
Requires-Dist: numpy>=2.0
Requires-Dist: pandas>=2.2
Provides-Extra: dev
Requires-Dist: pytest>=8.3; extra == "dev"
Requires-Dist: ruff>=0.6; extra == "dev"
Provides-Extra: docs
Requires-Dist: mkdocs>=1.6; extra == "docs"
Requires-Dist: mkdocs-material>=9.5; extra == "docs"
Requires-Dist: mkdocstrings[python]>=0.26; extra == "docs"
Provides-Extra: signatures
Requires-Dist: iisignature; extra == "signatures"
Dynamic: license-file
